README.rst
setup.py
PySpeedup.egg-info/PKG-INFO
PySpeedup.egg-info/SOURCES.txt
PySpeedup.egg-info/dependency_links.txt
PySpeedup.egg-info/top_level.txt
pyspeedup/__init__.py
pyspeedup/factored.py
pyspeedup/polynomial.py
pyspeedup/algorithms/Primes.py
pyspeedup/algorithms/_Shanks.py
pyspeedup/algorithms/__init__.py
pyspeedup/algorithms/_cached.py
pyspeedup/algorithms/_divideMod.py
pyspeedup/algorithms/_factor.py
pyspeedup/algorithms/_fibonacci.py
pyspeedup/algorithms/_gcd.py
pyspeedup/algorithms/_halfIterate.py
pyspeedup/algorithms/_indexCalculus.py
pyspeedup/algorithms/_invMod.py
pyspeedup/algorithms/_legendre.py
pyspeedup/algorithms/_pollard-rho.py
pyspeedup/algorithms/_primes.py
pyspeedup/algorithms/_squares.py
pyspeedup/concurrent/__init__.py
pyspeedup/concurrent/_buffer.py
pyspeedup/concurrent/_cache.py
pyspeedup/concurrent/_primer.py
pyspeedup/memory/__init__.py
pyspeedup/memory/_diskdict.py
pyspeedup/memory/_disklist.py
pyspeedup/memory/_ordereddiskdict.py
tests/__init__.py
tests/cacheTests.py