Metadata-Version: 1.1
Name: PySpeedup
Version: 0.1.2.2
Summary: A multiprocess framework for efficient calculations.
Home-page: http://pyspeedup.rtfd.org/
Author: Chris Dusold
Author-email: PySpeedup@ChrisDusold.com
License: The MIT License (MIT)
